ti-threatbook-api/__init__.py
ti-threatbook-api/client.py
ti-threatbook-api/exception.py
ti_threatbook_api/__init__.py
ti_threatbook_api/client.py
ti_threatbook_api/exception.py
ti_threatbook_api-0.0.1.dist-info/LICENSE
ti_threatbook_api-0.0.1.dist-info/METADATA
ti_threatbook_api-0.0.1.dist-info/WHEEL
ti_threatbook_api-0.0.1.dist-info/top_level.txt
ti_threatbook_api-0.0.1.dist-info/RECORD
